{"id":"0e3991311c","name":"호크헤드","gear":true,"hours":[0,0,0,0,0,0,0,0,0,0,0,1,0,0,1,0,0,0,0,0,0,0,0,0],"pct":[222222,222222,800000,800000,800000],"hmed":[null,null,null,null,null,null],"wmed":[null,null,null,null,null,null,null],"series":[{"d":"2025-12-20","p":222222,"a":222222,"lo":222222,"hi":222222,"n":1,"q":1,"dd":1},{"d":"2026-01-03","p":800000,"a":800000,"lo":800000,"hi":800000,"n":1,"q":1,"dd":1}],"recent":[{"d":"2026-01-03","t":"11:28:41","q":1,"u":800000,"o":"공격력 : 80, 업그레이드 가능 횟수 : 7"},{"d":"2025-12-20","t":"14:00:47","q":1,"u":222222,"o":"업그레이드 가능 횟수 : 7, 공격력 : 79"}]}