{"id":"4cee45a1b6","name":"미스릴 플라틴 바지","gear":true,"hours":[0,0,0,0,0,0,0,0,0,1,0,0,0,0,0,0,0,0,0,0,0,1,0,0],"pct":[499999,499999,500000,500000,500000],"hmed":[null,null,null,null,null,null],"wmed":[null,null,null,null,null,null,null],"series":[{"d":"2025-12-13","p":500000,"a":500000,"lo":500000,"hi":500000,"n":1,"q":1,"dd":1},{"d":"2026-02-11","p":499999,"a":499999,"lo":499999,"hi":499999,"n":1,"q":1,"dd":1}],"recent":[{"d":"2026-02-11","t":"09:27:22","q":1,"u":499999,"o":"명중률 : 1, 업그레이드 가능 횟수 : 7, 물리방어력 : 63, STR : 2"},{"d":"2025-12-13","t":"21:15:12","q":1,"u":500000,"o":"물리방어력 : 64, 업그레이드 가능 횟수 : 7, 명중률 : 2, STR : 2"}]}