{"id":"53f6bd071e","name":"화이트 네쉐르","gear":true,"hours":[0,0,0,0,0,0,0,0,0,0,0,0,0,2,0,1,0,0,1,0,2,2,1,0],"pct":[999999,1500000,2000000,2222222,399999999],"series":[{"d":"2026-07-06","p":999999,"lo":999999,"hi":999999,"n":1,"q":1},{"d":"2026-07-08","p":1555555,"lo":1555555,"hi":1555555,"n":1,"q":1},{"d":"2026-07-09","p":2000000,"lo":1500000,"hi":2222222,"n":3,"q":3},{"d":"2026-07-10","p":35000000,"lo":35000000,"hi":35000000,"n":1,"q":1},{"d":"2026-07-11","p":2000000,"lo":1200000,"hi":399999999,"n":3,"q":3}],"recent":[{"d":"2026-07-11","t":"15:35:59","q":1,"u":399999999,"o":"공격력 : 125, 명중률 : 15, 업그레이드 가능 횟수 : 0, 회피율 : 1, DEX : 5"},{"d":"2026-07-11","t":"13:37:00","q":1,"u":1200000,"o":"공격력 : 102, 업그레이드 가능 횟수 : 7"},{"d":"2026-07-11","t":"13:25:13","q":1,"u":2000000,"o":"업그레이드 가능 횟수 : 7, 공격력 : 102, 회피율 : 1"},{"d":"2026-07-10","t":"18:49:19","q":1,"u":35000000,"o":"업그레이드 가능 횟수 : 0, DEX : 2, 회피율 : 1, 명중률 : 8, 공격력 : 116"},{"d":"2026-07-09","t":"22:55:58","q":1,"u":1500000,"o":"회피율 : 1, 공격력 : 101, 업그레이드 가능 횟수 : 7"},{"d":"2026-07-09","t":"21:14:07","q":1,"u":2222222,"o":"공격력 : 101, 업그레이드 가능 횟수 : 7, 회피율 : 1"},{"d":"2026-07-09","t":"21:10:02","q":1,"u":2000000,"o":"업그레이드 가능 횟수 : 7, 회피율 : 1, 공격력 : 101"},{"d":"2026-07-08","t":"20:21:26","q":1,"u":1555555,"o":"업그레이드 가능 횟수 : 7, 공격력 : 101, 회피율 : 1"},{"d":"2026-07-06","t":"20:49:48","q":1,"u":999999,"o":"업그레이드 가능 횟수 : 7, 회피율 : 1, 공격력 : 100"}]}