{"id":"5a58febf06","name":"블루 레퀴엠","gear":true,"hours":[1,2,0,0,0,0,0,0,0,0,0,0,2,0,0,0,0,0,0,0,0,1,1,1],"pct":[450000,2500000,4000000,9999999,40000000],"hmed":[null,null,null,null,null,null],"wmed":[null,null,null,null,null,null,null],"series":[{"d":"2025-11-25","p":9999999,"a":9999999,"lo":9999999,"hi":9999999,"n":1,"q":1,"dd":1},{"d":"2025-11-28","p":3000000,"a":3000000,"lo":3000000,"hi":3000000,"n":1,"q":1,"dd":1},{"d":"2025-12-22","p":2500000,"a":2500000,"lo":2500000,"hi":2500000,"n":1,"q":1,"dd":1},{"d":"2026-01-20","p":450000,"a":450000,"lo":450000,"hi":450000,"n":1,"q":1,"dd":1},{"d":"2026-03-02","p":40000000,"a":40000000,"lo":40000000,"hi":40000000,"n":1,"q":1,"dd":1},{"d":"2026-03-22","p":4000000,"a":4000000,"lo":4000000,"hi":4000000,"n":1,"q":1,"dd":1},{"d":"2026-05-12","p":4000000,"a":4000000,"lo":4000000,"hi":4000000,"n":1,"q":1,"dd":1},{"d":"2026-06-17","p":1600000,"a":1600000,"lo":1600000,"hi":1600000,"n":1,"q":1,"dd":1}],"recent":[{"d":"2026-06-17","t":"12:44:41","q":1,"u":1600000,"o":"LUK : 8, 업그레이드 가능 횟수 : 10, MP : 30, INT : 2, 물리방어력 : 60, 마법방어력 : 33"},{"d":"2026-05-12","t":"00:47:25","q":1,"u":4000000,"o":"물리방어력 : 60, LUK : 18, MP : 30, INT : 2, 회피율 : 5, 업그레이드 가능 횟수 : 0, 마법방어력 : 30"},{"d":"2026-03-22","t":"01:16:22","q":1,"u":4000000,"o":"INT : 2, 마법방어력 : 32, MP : 30, LUK : 18, 회피율 : 6, 물리방어력 : 58, 업그레이드 가능 횟수 : 0"},{"d":"2026-03-02","t":"23:41:25","q":1,"u":40000000,"o":"MP : 31, LUK : 25, INT : 3, 회피율 : 9, 업그레이드 가능 횟수 : 0, 마법방어력 : 30, 물리방어력 : 60"},{"d":"2026-01-20","t":"12:55:06","q":1,"u":450000,"o":"업그레이드 가능 횟수 : 10, 물리방어력 : 61, MP : 31, 마법방어력 : 30, INT : 2, LUK : 5"},{"d":"2025-12-22","t":"01:13:55","q":1,"u":2500000,"o":"물리방어력 : 60, INT : 2, 마법방어력 : 33, LUK : 8, MP : 30, 업그레이드 가능 횟수 : 10"},{"d":"2025-11-28","t":"21:47:39","q":1,"u":3000000,"o":"마법방어력 : 32, 물리방어력 : 60, 업그레이드 가능 횟수 : 0, INT : 6, MP : 31, LUK : 16, 회피율 : 4"},{"d":"2025-11-25","t":"22:58:17","q":1,"u":9999999,"o":"회피율 : 7, LUK : 22, 업그레이드 가능 횟수 : 0, MP : 29, INT : 3, 물리방어력 : 59, 마법방어력 : 30"}]}