{"id":"f371868316","name":"마법의 가루(갈색)","gear":false,"hours":[1,2,2,0,0,0,0,0,1,0,0,0,0,1,0,1,0,1,1,1,1,0,1,2],"pct":[990,1333,1899,1999,5555],"series":[{"d":"2026-07-06","p":1899,"a":1727,"lo":1333,"hi":1999,"n":6,"q":26},{"d":"2026-07-09","p":5944.0,"a":5944,"lo":5555,"hi":6333,"n":2,"q":2},{"d":"2026-07-10","p":1999.0,"a":1999,"lo":1999,"hi":1999,"n":2,"q":15},{"d":"2026-07-11","p":1800.0,"a":1800,"lo":1800,"hi":1800,"n":2,"q":8},{"d":"2026-07-12","p":990,"a":990,"lo":990,"hi":990,"n":3,"q":3}],"recent":[{"d":"2026-07-12","t":"17:38:12","q":1,"u":990,"o":""},{"d":"2026-07-12","t":"15:43:22","q":1,"u":990,"o":""},{"d":"2026-07-12","t":"13:23:23","q":1,"u":990,"o":""},{"d":"2026-07-11","t":"02:46:28","q":1,"u":1800,"o":""},{"d":"2026-07-11","t":"02:09:46","q":7,"u":1800,"o":""},{"d":"2026-07-10","t":"23:11:54","q":14,"u":1999,"o":""},{"d":"2026-07-10","t":"23:08:50","q":1,"u":1999,"o":""},{"d":"2026-07-09","t":"20:57:41","q":1,"u":5555,"o":""},{"d":"2026-07-09","t":"18:33:12","q":1,"u":6333,"o":""},{"d":"2026-07-06","t":"22:25:25","q":1,"u":1899,"o":""},{"d":"2026-07-06","t":"19:10:57","q":1,"u":1899,"o":""},{"d":"2026-07-06","t":"08:43:37","q":1,"u":1900,"o":""},{"d":"2026-07-06","t":"01:14:38","q":20,"u":1999,"o":""},{"d":"2026-07-06","t":"01:14:25","q":2,"u":1333,"o":""},{"d":"2026-07-06","t":"00:41:21","q":1,"u":1333,"o":""}]}