{"id":"fc72a663be","name":"골든 네쉐르","gear":true,"series":[{"d":"2026-07-06","p":999999,"lo":999999,"hi":999999,"n":1,"q":1},{"d":"2026-07-07","p":5000000,"lo":5000000,"hi":5000000,"n":1,"q":1},{"d":"2026-07-08","p":5500000.0,"lo":1000000,"hi":14999999,"n":4,"q":4},{"d":"2026-07-09","p":2000000,"lo":2000000,"hi":2000000,"n":1,"q":1},{"d":"2026-07-11","p":999999,"lo":999999,"hi":999999,"n":1,"q":1},{"d":"2026-07-12","p":100000000,"lo":100000000,"hi":100000000,"n":1,"q":1}],"recent":[{"d":"2026-07-12","t":"02:30:49","q":1,"u":100000000,"o":"업그레이드 가능 횟수 : 0, DEX : 5, 공격력 : 123, 명중률 : 15, 점프력 : 3"},{"d":"2026-07-11","t":"13:35:53","q":1,"u":999999,"o":"점프력 : 3, 공격력 : 102, 업그레이드 가능 횟수 : 7"},{"d":"2026-07-09","t":"22:53:33","q":1,"u":2000000,"o":"공격력 : 102, 점프력 : 3, 업그레이드 가능 횟수 : 7"},{"d":"2026-07-08","t":"21:34:53","q":1,"u":5000000,"o":"공격력 : 102, 점프력 : 3, 업그레이드 가능 횟수 : 7"},{"d":"2026-07-08","t":"21:34:03","q":1,"u":6000000,"o":"공격력 : 102, 점프력 : 3, 업그레이드 가능 횟수 : 7"},{"d":"2026-07-08","t":"20:27:08","q":1,"u":1000000,"o":"공격력 : 100, 점프력 : 3, 업그레이드 가능 횟수 : 7"},{"d":"2026-07-08","t":"19:56:54","q":1,"u":14999999,"o":"명중률 : 7, 업그레이드 가능 횟수 : 0, 공격력 : 113, DEX : 1, 점프력 : 3"},{"d":"2026-07-07","t":"01:45:10","q":1,"u":5000000,"o":"업그레이드 가능 횟수 : 7, 점프력 : 3, 공격력 : 102"},{"d":"2026-07-06","t":"20:49:35","q":1,"u":999999,"o":"점프력 : 3, 업그레이드 가능 횟수 : 7, 공격력 : 100"}]}